chargemaster_parsers/__init__.py
chargemaster_parsers/parsers/__init__.py
chargemaster_parsers/parsers/cedars_sinai.py
chargemaster_parsers/parsers/kaiser.py
chargemaster_parsers/parsers/palomar.py
chargemaster_parsers/parsers/parsers.py
chargemaster_parsers/parsers/rady.py
chargemaster_parsers/parsers/scripps.py
chargemaster_parsers/parsers/sharp.py
chargemaster_parsers/parsers/southwest.py
chargemaster_parsers/parsers/stanford.py
chargemaster_parsers/parsers/uci.py
chargemaster_parsers/parsers/ucsd.py
chargemaster_parsers-0.0.4.dist-info/LICENSE
chargemaster_parsers-0.0.4.dist-info/METADATA
chargemaster_parsers-0.0.4.dist-info/WHEEL
chargemaster_parsers-0.0.4.dist-info/top_level.txt
chargemaster_parsers-0.0.4.dist-info/RECORD
