Metadata-Version: 2.1
Name: chargemaster-parsers
Version: 0.0.4
Summary: A library for parsing machine readable healthcare chargemasters
Author: Jacob Schaer, Yvonne Kaire
Project-URL: Homepage, https://github.com/jacobschaer/chargemaster_parsers
Classifier: Programming Language :: Python :: 3
Classifier: License :: OSI Approved :: MIT License
Classifier: Operating System :: OS Independent
Requires-Python: >=3.9
License-File: LICENSE
Requires-Dist: openpyxl (==3.1.2)
